{
  "unversionedId": "SD Card/statInfo/wthrVals.csv/index",
  "id": "SD Card/statInfo/wthrVals.csv/index",
  "title": "wthrvals.csv",
  "description": "📝 Written by: Weather Station",
  "source": "@site/docs/SD Card/statInfo/wthrVals.csv/index.md",
  "sourceDirName": "SD Card/statInfo/wthrVals.csv",
  "slug": "/SD Card/statInfo/wthrVals.csv/",
  "permalink": "/docs/SD Card/statInfo/wthrVals.csv/",
  "draft": false,
  "editUrl": "https://github.com/facebook/docusaurus/tree/main/packages/create-docusaurus/templates/shared/docs/SD Card/statInfo/wthrVals.csv/index.md",
  "tags": [],
  "version": "current",
  "frontMatter": {},
  "sidebar": "tutorialSidebar",
  "previous": {
    "title": "errorlog.txt",
    "permalink": "/docs/SD Card/statInfo/errorlog.txt/"
  },
  "next": {
    "title": "statOpts",
    "permalink": "/docs/SD Card/statOpts/"
  }
}